mfisp_boxdetection/__init__.py
mfisp_boxdetection/boxdetection.py
mfisp_boxdetection-0.0.1.dev1.dist-info/DESCRIPTION.rst
mfisp_boxdetection-0.0.1.dev1.dist-info/METADATA
mfisp_boxdetection-0.0.1.dev1.dist-info/RECORD
mfisp_boxdetection-0.0.1.dev1.dist-info/WHEEL
mfisp_boxdetection-0.0.1.dev1.dist-info/metadata.json
mfisp_boxdetection-0.0.1.dev1.dist-info/top_level.txt
