Metadata-Version: 2.0
Name: mfisp-boxdetection
Version: 0.0.1.dev1
Summary: mfisp-boxdetection
Home-page: https://github.com/csachs/mfisp-boxdetection
Author: Christian C. Sachs
Author-email: sachs.christian@gmail.com
License: UNKNOWN
Platform: UNKNOWN
Classifier: Development Status :: 4 - Beta
Classifier: Environment :: Console
Classifier: Intended Audience :: Science/Research
Classifier: License :: OSI Approved :: BSD License
Classifier: Operating System :: POSIX
Classifier: Operating System :: POSIX :: Linux
Classifier: Operating System :: MacOS :: MacOS X
Classifier: Operating System :: Microsoft :: Windows
Classifier: Topic :: Scientific/Engineering :: Bio-Informatics
Classifier: Topic :: Scientific/Engineering :: Image Recognition
Requires-Dist: molyso
Requires-Dist: numpy
